{
	"status": "success",
	"title": "미장센 디지털 필름",
	"link": "http://template.atail.itembridge.com/projects/Chinese-girl-posing.html",
	"content": "고데기 홈쇼핑 Fake영상에 유준호 더빙을 더해 에피소드를 연출하면서 자연스럽게 헤어 제품 커뮤니케이션",
	"date": "<span class=\"atail-project-date\"><span class=\"atail-proj-date-text\">Finished </span><span class=\"atail-proj-date-value\">- 22 Jun 2016</span></span>",
	"thumbnail": "<img width=\"1200\" height=\"911\" src=\"img/1_pr_ad_grandeur_thum.jpg\" alt=\"pexels-photo-69494\" />",
	"thumbnail_url": "img/1_pr_ad_grandeur_thum.jpg",
	"positions": null,
	"token": "865fc8f5ec",
	"participants": "<span class=\"post-content-footer-title\"></span>",
	"slides": [
    {
      "src": "https://www.youtube.com/embed/6uHANGTUqiY",
      "type": "video"
    },
        {
			"src": {
				"img": "img/project-preview/6_ad_amorepacific_1.jpg",
				"title": "",
				"text": "",
				"fit": "cover"
			},
			"fit": "cover",
			"type": "image"
		},
        {
			"src": {
				"img": "img/project-preview/6_ad_amorepacific_2.jpg",
				"title": "",
				"text": "",
				"fit": "cover"
			},
			"fit": "cover",
			"type": "image"
		}
	],
    "positions": [
    {
      "title": "Business",
      "url": "Advertising & Marketing"
    },
    {
      "title": "Project",
      "url": "Viral Film"
    }
  ]
}